ALU/modules/gates.v
// XOR OR AND operations on 64 bit data

// Due to provided design constraints the following is being done 

module xor_1bit (

    input a,
    input b,

    output c

); 

    assign c = a ^ b;

endmodule

module xor_4bit (

    input [3:0] a,
    input [3:0] b,

    output [3:0] c

);

    xor_1bit instance1 (.a(a[0]), .b(b[0]), .c(c[0]));
    xor_1bit instance2 (.a(a[1]), .b(b[1]), .c(c[1]));
    xor_1bit instance3 (.a(a[2]), .b(b[2]), .c(c[2]));
    xor_1bit instance4 (.a(a[3]), .b(b[3]), .c(c[3]));

endmodule

module xor_16bit (

    input [15:0] a,
    input [15:0] b,

    output [15:0] c

);

    xor_4bit instance1 (.a(a[3:0]), .b(b[3:0]), .c(c[3:0]));
    xor_4bit instance2 (.a(a[7:4]), .b(b[7:4]), .c(c[7:4]));
    xor_4bit instance3 (.a(a[11:8]), .b(b[11:8]), .c(c[11:8]));
    xor_4bit instance4 (.a(a[15:12]), .b(b[15:12]), .c(c[15:12]));

endmodule

module xor_64bit (

    input [63:0] a,
    input [63:0] b,

    output [63:0] c

);

    xor_16bit instance1 (.a(a[15:0]), .b(b[15:0]), .c(c[15:0]));
    xor_16bit instance2 (.a(a[31:16]), .b(b[31:16]), .c(c[31:16]));
    xor_16bit instance3 (.a(a[47:32]), .b(b[47:32]), .c(c[47:32]));
    xor_16bit instance4 (.a(a[63:48]), .b(b[63:48]), .c(c[63:48]));

endmodule

ALU/testbench/_gates_tb.v
`timescale 1ns/1ps

module testbench;

    reg [63:0] a,b;

    wire [63:0] c;

    xor_64bit uut (.a(a), .b(b), .c(c)); 

    initial begin
        
        $dumpfile("GTK/gates64bit.vcd");
        $dumpvars(0, testbench);

        // Gpt generated test cases

        // --------------------
        // BASIC cases
        // --------------------

        // 0 ^ 0 = 0
        a = 64'd0;
        b = 64'd0;
        #10;

        // 1 ^ 0 = 1
        a = 64'd1;
        b = 64'd0;
        #10;

        // 1 ^ 1 = 0
        a = 64'd1;
        b = 64'd1;
        #10;

        // --------------------
        // Pattern tests
        // --------------------

        // all 0s ^ all 1s = all 1s
        a = 64'h0000000000000000;
        b = 64'hFFFFFFFFFFFFFFFF;
        #10;

        // all 1s ^ all 1s = 0
        a = 64'hFFFFFFFFFFFFFFFF;
        b = 64'hFFFFFFFFFFFFFFFF;
        #10;

        // alternating bits
        a = 64'hAAAAAAAAAAAAAAAA; // 1010...
        b = 64'h5555555555555555; // 0101...
        #10;

        // --------------------
        // Random-looking values
        // --------------------

        a = 64'h123456789ABCDEF0;
        b = 64'h0F0F0F0F0F0F0F0F;
        #10;

        a = 64'h8000000000000000;
        b = 64'h0000000000000001;
        #10;

        // --------------------
        // Self XOR (must be zero)
        // --------------------

        a = 64'hDEAABEEECAAEBEBE;
        b = 64'hDEAABEEECAAEBEBE;
        #10;

        $finish;

    end


endmodule

ALU/GTK/gates64bit.vcd
$date
	Sun Feb  1 15:46:11 2026
$end
$version
	Icarus Verilog
$end
$timescale
	1ps
$end
$scope module testbench $end
$var wire 64 ! c [63:0] $end
$var reg 64 " a [63:0] $end
$var reg 64 # b [63:0] $end
$scope module uut $end
$var wire 64 $ a [63:0] $end
$var wire 64 % b [63:0] $end
$var wire 64 & c [63:0] $end
$scope module instance1 $end
$var wire 16 ' a [15:0] $end
$var wire 16 ( b [15:0] $end
$var wire 16 ) c [15:0] $end
$scope module instance1 $end
$var wire 4 * a [3:0] $end
$var wire 4 + b [3:0] $end
$var wire 4 , c [3:0] $end
$scope module instance1 $end
$var wire 1 - a $end
$var wire 1 . b $end
$var wire 1 / c $end
$upscope $end
$scope module instance2 $end
$var wire 1 0 a $end
$var wire 1 1 b $end
$var wire 1 2 c $end
$upscope $end
$scope module instance3 $end
$var wire 1 3 a $end
$var wire 1 4 b $end
$var wire 1 5 c $end
$upscope $end
$scope module instance4 $end
$var wire 1 6 a $end
$var wire 1 7 b $end
$var wire 1 8 c $end
$upscope $end
$upscope $end
$scope module instance2 $end
$var wire 4 9 a [3:0] $end
$var wire 4 : b [3:0] $end
$var wire 4 ; c [3:0] $end
$scope module instance1 $end
$var wire 1 < a $end
$var wire 1 = b $end
$var wire 1 > c $end
$upscope $end
$scope module instance2 $end
$var wire 1 ? a $end
$var wire 1 @ b $end
$var wire 1 A c $end
$upscope $end
$scope module instance3 $end
$var wire 1 B a $end
$var wire 1 C b $end
$var wire 1 D c $end
$upscope $end
$scope module instance4 $end
$var wire 1 E a $end
$var wire 1 F b $end
$var wire 1 G c $end
$upscope $end
$upscope $end
$scope module instance3 $end
$var wire 4 H a [3:0] $end
$var wire 4 I b [3:0] $end
$var wire 4 J c [3:0] $end
$scope module instance1 $end
$var wire 1 K a $end
$var wire 1 L b $end
$var wire 1 M c $end
$upscope $end
$scope module instance2 $end
$var wire 1 N a $end
$var wire 1 O b $end
$var wire 1 P c $end
$upscope $end
$scope module instance3 $end
$var wire 1 Q a $end
$var wire 1 R b $end
$var wire 1 S c $end
$upscope $end
$scope module instance4 $end
$var wire 1 T a $end
$var wire 1 U b $end
$var wire 1 V c $end
$upscope $end
$upscope $end
$scope module instance4 $end
$var wire 4 W a [3:0] $end
$var wire 4 X b [3:0] $end
$var wire 4 Y c [3:0] $end
$scope module instance1 $end
$var wire 1 Z a $end
$var wire 1 [ b $end
$var wire 1 \ c $end
$upscope $end
$scope module instance2 $end
$var wire 1 ] a $end
$var wire 1 ^ b $end
$var wire 1 _ c $end
$upscope $end
$scope module instance3 $end
$var wire 1 ` a $end
$var wire 1 a b $end
$var wire 1 b c $end
$upscope $end
$scope module instance4 $end
$var wire 1 c a $end
$var wire 1 d b $end
$var wire 1 e c $end
$upscope $end
$upscope $end
$upscope $end
$scope module instance2 $end
$var wire 16 f a [15:0] $end
$var wire 16 g b [15:0] $end
$var wire 16 h c [15:0] $end
$scope module instance1 $end
$var wire 4 i a [3:0] $end
$var wire 4 j b [3:0] $end
$var wire 4 k c [3:0] $end
$scope module instance1 $end
$var wire 1 l a $end
$var wire 1 m b $end
$var wire 1 n c $end
$upscope $end
$scope module instance2 $end
$var wire 1 o a $end
$var wire 1 p b $end
$var wire 1 q c $end
$upscope $end
$scope module instance3 $end
$var wire 1 r a $end
$var wire 1 s b $end
$var wire 1 t c $end
$upscope $end
$scope module instance4 $end
$var wire 1 u a $end
$var wire 1 v b $end
$var wire 1 w c $end
$upscope $end
$upscope $end
$scope module instance2 $end
$var wire 4 x a [3:0] $end
$var wire 4 y b [3:0] $end
$var wire 4 z c [3:0] $end
$scope module instance1 $end
$var wire 1 { a $end
$var wire 1 | b $end
$var wire 1 } c $end
$upscope $end
$scope module instance2 $end
$var wire 1 ~ a $end
$var wire 1 !" b $end
$var wire 1 "" c $end
$upscope $end
$scope module instance3 $end
$var wire 1 #" a $end
$var wire 1 $" b $end
$var wire 1 %" c $end
$upscope $end
$scope module instance4 $end
$var wire 1 &" a $end
$var wire 1 '" b $end
$var wire 1 (" c $end
$upscope $end
$upscope $end
$scope module instance3 $end
$var wire 4 )" a [3:0] $end
$var wire 4 *" b [3:0] $end
$var wire 4 +" c [3:0] $end
$scope module instance1 $end
$var wire 1 ," a $end
$var wire 1 -" b $end
$var wire 1 ." c $end
$upscope $end
$scope module instance2 $end
$var wire 1 /" a $end
$var wire 1 0" b $end
$var wire 1 1" c $end
$upscope $end
$scope module instance3 $end
$var wire 1 2" a $end
$var wire 1 3" b $end
$var wire 1 4" c $end
$upscope $end
$scope module instance4 $end
$var wire 1 5" a $end
$var wire 1 6" b $end
$var wire 1 7" c $end
$upscope $end
$upscope $end
$scope module instance4 $end
$var wire 4 8" a [3:0] $end
$var wire 4 9" b [3:0] $end
$var wire 4 :" c [3:0] $end
$scope module instance1 $end
$var wire 1 ;" a $end
$var wire 1 <" b $end
$var wire 1 =" c $end
$upscope $end
$scope module instance2 $end
$var wire 1 >" a $end
$var wire 1 ?" b $end
$var wire 1 @" c $end
$upscope $end
$scope module instance3 $end
$var wire 1 A" a $end
$var wire 1 B" b $end
$var wire 1 C" c $end
$upscope $end
$scope module instance4 $end
$var wire 1 D" a $end
$var wire 1 E" b $end
$var wire 1 F" c $end
$upscope $end
$upscope $end
$upscope $end
$scope module instance3 $end
$var wire 16 G" a [15:0] $end
$var wire 16 H" b [15:0] $end
$var wire 16 I" c [15:0] $end
$scope module instance1 $end
$var wire 4 J" a [3:0] $end
$var wire 4 K" b [3:0] $end
$var wire 4 L" c [3:0] $end
$scope module instance1 $end
$var wire 1 M" a $end
$var wire 1 N" b $end
$var wire 1 O" c $end
$upscope $end
$scope module instance2 $end
$var wire 1 P" a $end
$var wire 1 Q" b $end
$var wire 1 R" c $end
$upscope $end
$scope module instance3 $end
$var wire 1 S" a $end
$var wire 1 T" b $end
$var wire 1 U" c $end
$upscope $end
$scope module instance4 $end
$var wire 1 V" a $end
$var wire 1 W" b $end
$var wire 1 X" c $end
$upscope $end
$upscope $end
$scope module instance2 $end
$var wire 4 Y" a [3:0] $end
$var wire 4 Z" b [3:0] $end
$var wire 4 [" c [3:0] $end
$scope module instance1 $end
$var wire 1 \" a $end
$var wire 1 ]" b $end
$var wire 1 ^" c $end
$upscope $end
$scope module instance2 $end
$var wire 1 _" a $end
$var wire 1 `" b $end
$var wire 1 a" c $end
$upscope $end
$scope module instance3 $end
$var wire 1 b" a $end
$var wire 1 c" b $end
$var wire 1 d" c $end
$upscope $end
$scope module instance4 $end
$var wire 1 e" a $end
$var wire 1 f" b $end
$var wire 1 g" c $end
$upscope $end
$upscope $end
$scope module instance3 $end
$var wire 4 h" a [3:0] $end
$var wire 4 i" b [3:0] $end
$var wire 4 j" c [3:0] $end
$scope module instance1 $end
$var wire 1 k" a $end
$var wire 1 l" b $end
$var wire 1 m" c $end
$upscope $end
$scope module instance2 $end
$var wire 1 n" a $end
$var wire 1 o" b $end
$var wire 1 p" c $end
$upscope $end
$scope module instance3 $end
$var wire 1 q" a $end
$var wire 1 r" b $end
$var wire 1 s" c $end
$upscope $end
$scope module instance4 $end
$var wire 1 t" a $end
$var wire 1 u" b $end
$var wire 1 v" c $end
$upscope $end
$upscope $end
$scope module instance4 $end
$var wire 4 w" a [3:0] $end
$var wire 4 x" b [3:0] $end
$var wire 4 y" c [3:0] $end
$scope module instance1 $end
$var wire 1 z" a $end
$var wire 1 {" b $end
$var wire 1 |" c $end
$upscope $end
$scope module instance2 $end
$var wire 1 }" a $end
$var wire 1 ~" b $end
$var wire 1 !# c $end
$upscope $end
$scope module instance3 $end
$var wire 1 "# a $end
$var wire 1 ## b $end
$var wire 1 $# c $end
$upscope $end
$scope module instance4 $end
$var wire 1 %# a $end
$var wire 1 &# b $end
$var wire 1 '# c $end
$upscope $end
$upscope $end
$upscope $end
$scope module instance4 $end
$var wire 16 (# a [15:0] $end
$var wire 16 )# b [15:0] $end
$var wire 16 *# c [15:0] $end
$scope module instance1 $end
$var wire 4 +# a [3:0] $end
$var wire 4 ,# b [3:0] $end
$var wire 4 -# c [3:0] $end
$scope module instance1 $end
$var wire 1 .# a $end
$var wire 1 /# b $end
$var wire 1 0# c $end
$upscope $end
$scope module instance2 $end
$var wire 1 1# a $end
$var wire 1 2# b $end
$var wire 1 3# c $end
$upscope $end
$scope module instance3 $end
$var wire 1 4# a $end
$var wire 1 5# b $end
$var wire 1 6# c $end
$upscope $end
$scope module instance4 $end
$var wire 1 7# a $end
$var wire 1 8# b $end
$var wire 1 9# c $end
$upscope $end
$upscope $end
$scope module instance2 $end
$var wire 4 :# a [3:0] $end
$var wire 4 ;# b [3:0] $end
$var wire 4 <# c [3:0] $end
$scope module instance1 $end
$var wire 1 =# a $end
$var wire 1 ># b $end
$var wire 1 ?# c $end
$upscope $end
$scope module instance2 $end
$var wire 1 @# a $end
$var wire 1 A# b $end
$var wire 1 B# c $end
$upscope $end
$scope module instance3 $end
$var wire 1 C# a $end
$var wire 1 D# b $end
$var wire 1 E# c $end
$upscope $end
$scope module instance4 $end
$var wire 1 F# a $end
$var wire 1 G# b $end
$var wire 1 H# c $end
$upscope $end
$upscope $end
$scope module instance3 $end
$var wire 4 I# a [3:0] $end
$var wire 4 J# b [3:0] $end
$var wire 4 K# c [3:0] $end
$scope module instance1 $end
$var wire 1 L# a $end
$var wire 1 M# b $end
$var wire 1 N# c $end
$upscope $end
$scope module instance2 $end
$var wire 1 O# a $end
$var wire 1 P# b $end
$var wire 1 Q# c $end
$upscope $end
$scope module instance3 $end
$var wire 1 R# a $end
$var wire 1 S# b $end
$var wire 1 T# c $end
$upscope $end
$scope module instance4 $end
$var wire 1 U# a $end
$var wire 1 V# b $end
$var wire 1 W# c $end
$upscope $end
$upscope $end
$scope module instance4 $end
$var wire 4 X# a [3:0] $end
$var wire 4 Y# b [3:0] $end
$var wire 4 Z# c [3:0] $end
$scope module instance1 $end
$var wire 1 [# a $end
$var wire 1 \# b $end
$var wire 1 ]# c $end
$upscope $end
$scope module instance2 $end
$var wire 1 ^# a $end
$var wire 1 _# b $end
$var wire 1 `# c $end
$upscope $end
$scope module instance3 $end
$var wire 1 a# a $end
$var wire 1 b# b $end
$var wire 1 c# c $end
$upscope $end
$scope module instance4 $end
$var wire 1 d# a $end
$var wire 1 e# b $end
$var wire 1 f# c $end
$upscope $end
$upscope $end
$upscope $end
$upscope $end
$upscope $end
$enddefinitions $end
$comment Show the parameter values. $end
$dumpall
$end
#0
$dumpvars
0f#
0e#
0d#
0c#
0b#
0a#
0`#
0_#
0^#
0]#
0\#
0[#
b0 Z#
b0 Y#
b0 X#
0W#
0V#
0U#
0T#
0S#
0R#
0Q#
0P#
0O#
0N#
0M#
0L#
b0 K#
b0 J#
b0 I#
0H#
0G#
0F#
0E#
0D#
0C#
0B#
0A#
0@#
0?#
0>#
0=#
b0 <#
b0 ;#
b0 :#
09#
08#
07#
06#
05#
04#
03#
02#
01#
00#
0/#
0.#
b0 -#
b0 ,#
b0 +#
b0 *#
b0 )#
b0 (#
0'#
0&#
0%#
0$#
0##
0"#
0!#
0~"
0}"
0|"
0{"
0z"
b0 y"
b0 x"
b0 w"
0v"
0u"
0t"
0s"
0r"
0q"
0p"
0o"
0n"
0m"
0l"
0k"
b0 j"
b0 i"
b0 h"
0g"
0f"
0e"
0d"
0c"
0b"
0a"
0`"
0_"
0^"
0]"
0\"
b0 ["
b0 Z"
b0 Y"
0X"
0W"
0V"
0U"
0T"
0S"
0R"
0Q"
0P"
0O"
0N"
0M"
b0 L"
b0 K"
b0 J"
b0 I"
b0 H"
b0 G"
0F"
0E"
0D"
0C"
0B"
0A"
0@"
0?"
0>"
0="
0<"
0;"
b0 :"
b0 9"
b0 8"
07"
06"
05"
04"
03"
02"
01"
00"
0/"
0."
0-"
0,"
b0 +"
b0 *"
b0 )"
0("
0'"
0&"
0%"
0$"
0#"
0""
0!"
0~
0}
0|
0{
b0 z
b0 y
b0 x
0w
0v
0u
0t
0s
0r
0q
0p
0o
0n
0m
0l
b0 k
b0 j
b0 i
b0 h
b0 g
b0 f
0e
0d
0c
0b
0a
0`
0_
0^
0]
0\
0[
0Z
b0 Y
b0 X
b0 W
0V
0U
0T
0S
0R
0Q
0P
0O
0N
0M
0L
0K
b0 J
b0 I
b0 H
0G
0F
0E
0D
0C
0B
0A
0@
0?
0>
0=
0<
b0 ;
b0 :
b0 9
08
07
06
05
04
03
02
01
00
0/
0.
0-
b0 ,
b0 +
b0 *
b0 )
b0 (
b0 '
b0 &
b0 %
b0 $
b0 #
b0 "
b0 !
$end
#10000
b1 !
b1 &
b1 )
b1 ,
1/
1-
b1 *
b1 '
b1 "
b1 $
#20000
b0 !
b0 &
b0 )
b0 ,
0/
1.
b1 +
b1 (
b1 #
b1 %
#30000
12
15
18
1>
1A
1D
b1111 ;
1G
1M
1P
1S
b1111 J
1V
1\
1_
1b
b1111 Y
1e
1n
1q
1t
b1111 k
1w
1}
1""
1%"
b1111 z
1("
1."
11"
14"
b1111 +"
17"
1="
1@"
1C"
b1111111111111111 h
b1111 :"
1F"
1O"
1R"
1U"
b1111 L"
1X"
1^"
1a"
1d"
b1111 ["
1g"
1m"
1p"
1s"
b1111 j"
1v"
1|"
1!#
1$#
b1111111111111111 I"
b1111 y"
1'#
10#
13#
16#
b1111 -#
19#
1?#
1B#
1E#
b1111 <#
1H#
1N#
1Q#
1T#
b1111 K#
1W#
1]#
1`#
1c#
b1111111111111111 *#
b1111 Z#
1f#
b1111111111111111111111111111111111111111111111111111111111111111 !
b1111111111111111111111111111111111111111111111111111111111111111 &
b1111111111111111 )
b1111 ,
1/
11
14
17
1=
1@
1C
1F
1L
1O
1R
1U
1[
1^
1a
1d
1m
1p
1s
1v
1|
1!"
1$"
1'"
1-"
10"
13"
16"
1<"
1?"
1B"
1E"
1N"
1Q"
1T"
1W"
1]"
1`"
1c"
1f"
1l"
1o"
1r"
1u"
1{"
1~"
1##
1&#
1/#
12#
15#
18#
1>#
1A#
1D#
1G#
1M#
1P#
1S#
1V#
1\#
1_#
1b#
1e#
0-
b1111 +
b1111 :
b1111 I
b1111 X
b1111 j
b1111 y
b1111 *"
b1111 9"
b1111 K"
b1111 Z"
b1111 i"
b1111 x"
b1111 ,#
b1111 ;#
b1111 J#
b1111 Y#
b0 *
b1111111111111111 (
b1111111111111111 g
b1111111111111111 H"
b1111111111111111 )#
b0 '
b1111111111111111111111111111111111111111111111111111111111111111 #
b1111111111111111111111111111111111111111111111111111111111111111 %
b0 "
b0 $
#40000
0/
02
05
b0 ,
08
0>
0A
0D
b0 ;
0G
0M
0P
0S
b0 J
0V
0\
0_
0b
b0 )
b0 Y
0e
0n
0q
0t
b0 k
0w
0}
0""
0%"
b0 z
0("
0."
01"
04"
b0 +"
07"
0="
0@"
0C"
b0 h
b0 :"
0F"
0O"
0R"
0U"
b0 L"
0X"
0^"
0a"
0d"
b0 ["
0g"
0m"
0p"
0s"
b0 j"
0v"
0|"
0!#
0$#
b0 I"
b0 y"
0'#
00#
03#
06#
b0 -#
09#
0?#
0B#
0E#
b0 <#
0H#
0N#
0Q#
0T#
b0 K#
0W#
0]#
0`#
0c#
b0 !
b0 &
b0 *#
b0 Z#
0f#
1-
10
13
16
1<
1?
1B
1E
1K
1N
1Q
1T
1Z
1]
1`
1c
1l
1o
1r
1u
1{
1~
1#"
1&"
1,"
1/"
12"
15"
1;"
1>"
1A"
1D"
1M"
1P"
1S"
1V"
1\"
1_"
1b"
1e"
1k"
1n"
1q"
1t"
1z"
1}"
1"#
1%#
1.#
11#
14#
17#
1=#
1@#
1C#
1F#
1L#
1O#
1R#
1U#
1[#
1^#
1a#
1d#
b1111 *
b1111 9
b1111 H
b1111 W
b1111 i
b1111 x
b1111 )"
b1111 8"
b1111 J"
b1111 Y"
b1111 h"
b1111 w"
b1111 +#
b1111 :#
b1111 I#
b1111 X#
b1111111111111111 '
b1111111111111111 f
b1111111111111111 G"
b1111111111111111 (#
b1111111111111111111111111111111111111111111111111111111111111111 "
b1111111111111111111111111111111111111111111111111111111111111111 $
#50000
12
18
1A
1G
1P
1V
1_
1e
1q
1w
1""
1("
11"
17"
1@"
1F"
1R"
1X"
1a"
1g"
1p"
1v"
1!#
1'#
13#
19#
1B#
1H#
1Q#
1W#
1`#
1f#
1/
b1111 ,
15
1>
b1111 ;
1D
1M
b1111 J
1S
1\
b1111111111111111 )
b1111 Y
1b
1n
b1111 k
1t
1}
b1111 z
1%"
1."
b1111 +"
14"
1="
b1111111111111111 h
b1111 :"
1C"
1O"
b1111 L"
1U"
1^"
b1111 ["
1d"
1m"
b1111 j"
1s"
1|"
b1111111111111111 I"
b1111 y"
1$#
10#
b1111 -#
16#
1?#
b1111 <#
1E#
1N#
b1111 K#
1T#
1]#
b1111111111111111111111111111111111111111111111111111111111111111 !
b1111111111111111111111111111111111111111111111111111111111111111 &
b1111111111111111 *#
b1111 Z#
1c#
01
07
0@
0F
0O
0U
0^
0d
0p
0v
0!"
0'"
00"
06"
0?"
0E"
0Q"
0W"
0`"
0f"
0o"
0u"
0~"
0&#
02#
08#
0A#
0G#
0P#
0V#
0_#
0e#
0-
03
0<
0B
0K
0Q
0Z
0`
0l
0r
0{
0#"
0,"
02"
0;"
0A"
0M"
0S"
0\"
0b"
0k"
0q"
0z"
0"#
0.#
04#
0=#
0C#
0L#
0R#
0[#
0a#
b101 +
b101 :
b101 I
b101 X
b101 j
b101 y
b101 *"
b101 9"
b101 K"
b101 Z"
b101 i"
b101 x"
b101 ,#
b101 ;#
b101 J#
b101 Y#
b1010 *
b1010 9
b1010 H
b1010 W
b1010 i
b1010 x
b1010 )"
b1010 8"
b1010 J"
b1010 Y"
b1010 h"
b1010 w"
b1010 +#
b1010 :#
b1010 I#
b1010 X#
b101010101010101 (
b101010101010101 g
b101010101010101 H"
b101010101010101 )#
b1010101010101010 '
b1010101010101010 f
b1010101010101010 G"
b1010101010101010 (#
b101010101010101010101010101010101010101010101010101010101010101 #
b101010101010101010101010101010101010101010101010101010101010101 %
b1010101010101010101010101010101010101010101010101010101010101010 "
b1010101010101010101010101010101010101010101010101010101010101010 $
#60000
0P
0V
0w
b1011 z
0%"
01"
b101 +"
07"
0C"
b111 L"
0X"
0p"
0E#
b1101 K#
0Q#
0c#
b1 J
0S
b1101000111111111 )
b1101 Y
0_
b11 k
0t
b1001010110110011 h
b1001 :"
0@"
b111 ["
0g"
b1001 j"
0s"
0!#
b101100101110111 I"
b101 y"
0'#
b1011 -#
06#
b11 <#
0H#
0`#
b1110100111011010110010111011110010101101100111101000111111111 !
b1110100111011010110010111011110010101101100111101000111111111 &
b1110100111011 *#
b1 Z#
0f#
11
17
0=
0C
1O
1U
0[
0a
1p
1v
0|
0$"
10"
16"
0<"
0B"
1Q"
1W"
0]"
0c"
1o"
1u"
0{"
0##
12#
18#
0>#
0D#
1P#
1V#
0\#
0b#
00
06
1<
1B
1Q
1Z
0]
1`
0o
1r
1{
1;"
0>"
0P"
1\"
1b"
0e"
1q"
0t"
1z"
0}"
1"#
0%#
01#
14#
07#
1=#
0F#
0U#
1[#
0^#
0d#
b1111 +
b0 :
b1111 I
b0 X
b1111 j
b0 y
b1111 *"
b0 9"
b1111 K"
b0 Z"
b1111 i"
b0 x"
b1111 ,#
b0 ;#
b1111 J#
b0 Y#
b0 *
b1111 9
b1110 H
b1101 W
b1100 i
b1011 x
b1001 8"
b1000 J"
b111 Y"
b110 h"
b101 w"
b100 +#
b11 :#
b10 I#
b1 X#
b111100001111 (
b111100001111 g
b111100001111 H"
b111100001111 )#
b1101111011110000 '
b1001101010111100 f
b101011001111000 G"
b1001000110100 (#
b111100001111000011110000111100001111000011110000111100001111 #
b111100001111000011110000111100001111000011110000111100001111 %
b1001000110100010101100111100010011010101111001101111011110000 "
b1001000110100010101100111100010011010101111001101111011110000 $
#70000
02
05
b1 ,
08
b0 J
0M
0n
b0 k
0q
0."
b0 +"
04"
0O"
0R"
b0 L"
0U"
0m"
b0 j"
0v"
00#
03#
b0 -#
09#
0N#
0T#
b0 K#
0W#
0>
0A
0D
b0 ;
0G
0\
0b
b1 )
b0 Y
0e
0}
0""
b0 z
0("
0="
b0 h
b0 :"
0F"
0^"
0a"
b0 ["
0d"
0|"
b0 I"
b0 y"
0$#
0?#
b0 <#
0B#
0]#
b1000000000000000000000000000000000000000000000000000000000000001 !
b1000000000000000000000000000000000000000000000000000000000000001 &
b1000000000000000 *#
b1000 Z#
1f#
01
04
07
0L
0O
0R
0U
0m
0p
0s
0v
0-"
00"
03"
06"
0N"
0Q"
0T"
0W"
0l"
0o"
0r"
0u"
0/#
02#
05#
08#
0M#
0P#
0S#
0V#
0<
0?
0B
0E
0N
0Q
0T
0Z
0`
0c
0r
0u
0{
0~
0&"
0/"
05"
0;"
0D"
0V"
0\"
0_"
0b"
0n"
0q"
0z"
0"#
04#
0=#
0@#
0O#
0[#
1d#
b1 +
b0 I
b0 j
b0 *"
b0 K"
b0 i"
b0 ,#
b0 J#
b0 9
b0 H
b0 W
b0 i
b0 x
b0 )"
b0 8"
b0 J"
b0 Y"
b0 h"
b0 w"
b0 +#
b0 :#
b0 I#
b1000 X#
b1 (
b0 g
b0 H"
b0 )#
b0 '
b0 f
b0 G"
b1000000000000000 (#
b1 #
b1 %
b1000000000000000000000000000000000000000000000000000000000000000 "
b1000000000000000000000000000000000000000000000000000000000000000 $
#80000
b0 )
b0 ,
0/
b0 !
b0 &
b0 *#
b0 Z#
0f#
0.
11
14
17
1=
1@
1F
1O
1R
1U
1[
1^
1d
1p
1s
1v
1!"
1'"
10"
16"
1B"
1E"
1Q"
1T"
1W"
1`"
1c"
1f"
1o"
1r"
1u"
1{"
1~"
1&#
12#
18#
1A#
1G#
1P#
1S#
1V#
1\#
1b#
1e#
10
13
16
1<
1?
1E
1N
1Q
1T
1Z
1]
1c
1o
1r
1u
1~
1&"
1/"
15"
1A"
1D"
1P"
1S"
1V"
1_"
1b"
1e"
1n"
1q"
1t"
1z"
1}"
1%#
11#
17#
1@#
1F#
1O#
1R#
1U#
1[#
1a#
b1110 +
b1011 :
b1110 I
b1011 X
b1110 j
b1010 y
b1010 *"
b1100 9"
b1110 K"
b1110 Z"
b1110 i"
b1011 x"
b1010 ,#
b1010 ;#
b1110 J#
b1101 Y#
b1110 *
b1011 9
b1110 H
b1011 W
b1110 i
b1010 x
b1010 )"
b1100 8"
b1110 J"
b1110 Y"
b1110 h"
b1011 w"
b1010 +#
b1010 :#
b1110 I#
b1101 X#
b1011111010111110 (
b1100101010101110 g
b1011111011101110 H"
b1101111010101010 )#
b1011111010111110 '
b1100101010101110 f
b1011111011101110 G"
b1101111010101010 (#
b1101111010101010101111101110111011001010101011101011111010111110 #
b1101111010101010101111101110111011001010101011101011111010111110 %
b1101111010101010101111101110111011001010101011101011111010111110 "
b1101111010101010101111101110111011001010101011101011111010111110 $
